attackmate/__init__.py
attackmate/__main__.py
attackmate/attackmate.py
attackmate/command.py
attackmate/execexception.py
attackmate/logging_setup.py
attackmate/metadata.py
attackmate/playbook_parser.py
attackmate/processmanager.py
attackmate/result.py
attackmate/variablestore.py
attackmate/data/Father.tar.gz
attackmate/executors/__init__.py
attackmate/executors/baseexecutor.py
attackmate/executors/executor_factory.py
attackmate/executors/browser/browserexecutor.py
attackmate/executors/browser/sessionstore.py
attackmate/executors/common/debugexecutor.py
attackmate/executors/common/includeexecutor.py
attackmate/executors/common/jsonexecutor.py
attackmate/executors/common/loopexecutor.py
attackmate/executors/common/regexexecutor.py
attackmate/executors/common/setvarexecutor.py
attackmate/executors/common/sleepexecutor.py
attackmate/executors/common/tempfileexecutor.py
attackmate/executors/father/fatherexecutor.py
attackmate/executors/features/background.py
attackmate/executors/features/cmdvars.py
attackmate/executors/features/conditional.py
attackmate/executors/features/exitonerror.py
attackmate/executors/features/looper.py
attackmate/executors/http/httpclientexecutor.py
attackmate/executors/http/webservexecutor.py
attackmate/executors/metasploit/msfexecutor.py
attackmate/executors/metasploit/msfpayloadexecutor.py
attackmate/executors/metasploit/msfsessionexecutor.py
attackmate/executors/metasploit/msfsessionstore.py
attackmate/executors/shell/sessionstore.py
attackmate/executors/shell/shellexecutor.py
attackmate/executors/sliver/sliverexecutor.py
attackmate/executors/sliver/sliversessionexecutor.py
attackmate/executors/ssh/interactfeature.py
attackmate/executors/ssh/sessionstore.py
attackmate/executors/ssh/sftpfeature.py
attackmate/executors/ssh/sshexecutor.py
attackmate/executors/vnc/sessionstore.py
attackmate/executors/vnc/vncexecutor.py
attackmate/schemas/__init__.py
attackmate/schemas/base.py
attackmate/schemas/browser.py
attackmate/schemas/config.py
attackmate-0.6.0.dist-info/licenses/LICENSE
attackmate-0.6.0.dist-info/METADATA
attackmate-0.6.0.dist-info/WHEEL
attackmate-0.6.0.dist-info/entry_points.txt
attackmate-0.6.0.dist-info/top_level.txt
attackmate-0.6.0.dist-info/RECORD
