Metadata-Version: 2.4
Name: attackmate
Version: 0.6.0
Summary: AttackMate is an attack orchestration tool that executes full attack-chains based on playbooks.
Author-email: Wolfgang Hotwagner <wolfgang.hotwagner@ait.ac.at>
License: GPL-3.0
Keywords: Pentest,Attack,Orchestration,Hacking,Simulating,Attackchain
Requires-Python: >=3.7
License-File: LICENSE
Requires-Dist: pydantic~=2.5
Requires-Dist: colorlog
Requires-Dist: pymetasploit3
Requires-Dist: pyaml
Requires-Dist: paramiko
Requires-Dist: sliver-py
Requires-Dist: tabulate
Requires-Dist: python-magic
Requires-Dist: httpx
Requires-Dist: httpx[http2]
Requires-Dist: vncdotool
Requires-Dist: pytest-mock
Requires-Dist: playwright
Dynamic: license-file
